pytest_postgres/__init__.py
pytest_postgres/plugin.py
pytest_postgres-0.7.0.dist-info/LICENSE
pytest_postgres-0.7.0.dist-info/METADATA
pytest_postgres-0.7.0.dist-info/WHEEL
pytest_postgres-0.7.0.dist-info/entry_points.txt
pytest_postgres-0.7.0.dist-info/top_level.txt
pytest_postgres-0.7.0.dist-info/RECORD
